setup.py
lib/PyQCheck.egg-info/PKG-INFO
lib/PyQCheck.egg-info/SOURCES.txt
lib/PyQCheck.egg-info/dependency_links.txt
lib/PyQCheck.egg-info/top_level.txt
lib/pyqcheck/__init__.py
lib/pyqcheck/arbitrary.py
lib/pyqcheck/pyqworker.py
lib/pyqcheck/util.py
lib/pyqcheck/arbitraries/__init__.py
lib/pyqcheck/arbitraries/pq_boolean.py
lib/pyqcheck/arbitraries/pq_hiragana.py
lib/pyqcheck/arbitraries/pq_integer.py
lib/pyqcheck/arbitraries/pq_katakana.py
lib/pyqcheck/arbitraries/pq_momoclo.py
lib/pyqcheck/arbitraries/pq_number.py
lib/pyqcheck/arbitraries/pq_string.py