Metadata-Version: 1.1
Name: PyQCheck
Version: 0.3.4
Summary: PyQCheck is Quick Check-like random testing framework.
Home-page: https://github.com/futoase/PyQCheck
Author: Keiji Matsuzaki
Author-email: futoase@gmail.com
License: MIT License
Platform: UNKNOWN
Classifier: Programming Language :: Python :: 3.3
Classifier: Topic :: Software Development
